{
  "type": "minecraft:crafting_shaped",
  "pattern": [
    "PPI",
    "SRA",
    "PTI"
  ],
  "key": {
    "P": {
      "tag": "forge:plates/steel"
    },
    "A": {
      "item": "dynamicelectricity:alternator"
    },
    "R": {
      "item": "dynamicelectricity:shaftsteel"
    },
    "S": {
      "item": "dynamicelectricity:stator"
    },
    "T": {
      "item": "electrodynamics:tanksteel"
    },
    "I": {
      "item": "electrodynamics:insulation"
    }
  },
  "result": {
    "item": "dynamicelectricity:motordclv"
  }
}